ducttape/__init__.py
ducttape/crypt.py
ducttape/header.py
ducttape/lambdafier.py
ducttape/main.py
ducttape/stdlib.py
ducttape/tree.py
pyducttape-0.0.2.dist-info/LICENSE
pyducttape-0.0.2.dist-info/METADATA
pyducttape-0.0.2.dist-info/WHEEL
pyducttape-0.0.2.dist-info/entry_points.txt
pyducttape-0.0.2.dist-info/top_level.txt
pyducttape-0.0.2.dist-info/RECORD
