Metadata-Version: 2.1
Name: pyducttape
Version: 0.0.2
Summary: Package, encrypt and obfuscate Python scripts
Home-page: https://github.com/bpradana/ducttape
Author: Michael Williamson, Bintang Pradana Erlangga Putra
Author-email: mike@zwobble.org, work.bpradana@gmail.com
License: BSD-2-Clause
Requires-Python: >=3.5
License-File: LICENSE
Requires-Dist: astor
Requires-Dist: PyCryptodome
